Workbook

Sheet Input Guidlines
B5: In Summery sheet
A6: Yellow Cells | B6: Kindly key in the input values as per Car of your choice and applicable interest rate available in the car loan offering from market.
B8: In Comparison Sheet
A9: Yellow Cells | B9: Kindly key in the salary component values as per your Fixed CTC and salary components

Sheet Summary
B2: Enter Values for Cells Mentioned in Yellow Only | F2: Lease workings
B4: Car Cost Details
B6: Particulars | D6: Amt (in INR) | F6: Lease Tenure in years | G6: 3 | I6: 4 | K6: 5
B7: Basic Price | D7: =D9/(1+D21) -> 847457.63 | F7: Rate of GST | G7: 0.18 | H7: 0.4 | I7: 0.18 | J7: 0.4 | K7: 0.18 | L7: 0.4
B8: GST | D8: =+D7*D21 -> 152542.37 | F8: Lease Rental (pmpl) Finance Lease | G8: =3255+50 -> 3305 | H8: =3305+50 -> 3355 | I8: =2670+50 -> 2720 | J8: =2720+50 -> 2770 | K8: =2305+50 -> 2355 | L8: =2355+50 -> 2405
B9: Ex-Showroom Price | D9: 1000000 | F9: Residual value | G9: 0.1 | I9: 0.05 | K9: 0.01
B10: Discount | D10: 0
B11: Discounted Ex Showroom | D11: =D9-D10 -> 1000000
B12: Discounted Basic Price | D12: =D11/(1+D21) -> 847457.63 | F12: Lease Outflow for 3Yrs, 4Yrs and 5yrs
B13: GST | D13: =D12*D21 -> 152542.37 | F13: Tenure in Months | G13: Monthly Lease Rental | H13: Total Rental | I13: End Sale Value | J13: Income Tax Savings | K13: Effective Lease Outflow | L13: Net Savings in Lease
B14: Insurance (~44500)+ BH* Tentatively (35000)+ Reg Cost (14750) Fast Tag (700) Ext. Waranty +2 year/1 lakh Kms* (19156) Accessories (37498) | D14: =(35000+14750+700+19156+37498)*0+(44500)*0 -> 0 | F14: 36 | G14: ='3 Year RV @ 10% FL'!E18 -> 33050 | H14: =G14*F14 -> 1189800 | I14: ='3 Year RV @ 10% FL'!E55 -> 100000 | J14: ='3 Year RV @ 10% FL'!D12 -> 371217.6 | K14: =H14+I14-J14 -> 918582.4 | L14: =K20-K14 -> 205952.07
F15: 48 | G15: ='4 Year RV @ 5% FL'!E18 -> 27200 | H15: =G15*F15 -> 1305600 | I15: ='4 Year RV @ 5% FL'!E67 -> 50000 | J15: ='4 Year RV @ 5% FL'!D12 -> 407347.2 | K15: =H15+I15-J15 -> 948252.8 | L15: =K21-K15 -> 221168.69
B16: Other Discount | D16: 0 | F16: 60 | G16: ='5 Year RV @ 1% FL'!E18 -> 23550 | H16: =G16*F16 -> 1413000 | I16: ='5 Year RV @ 1% FL'!E79 -> 10000 | J16: ='5 Year RV @ 1% FL'!D12 -> 440856 | K16: =H16+I16-J16 -> 982144 | L16: =K22-K16 -> 233275.09
B17: TCS @ 1% | D17: =D11*1/100*0 -> 0
B18: On-Road Price | D18: =+D11+D14-D16+D17 -> 1000000 | F18: Loan Outflow
B19: Capitalization Cost | D19: =D18-D13-D17 -> 847457.63 | F19: Tenure in Months | G19: Monthly EMI | H19: Total EMI | I19: End Sale Value | J19: Income Tax Savings | K19: Effective Loan Outflow
F20: 36 | G20: ='3 Year RV @ 10% FL'!I18 -> 31237.069 | H20: =G20*F20 -> 1124534.5 | I20: 0 | J20: 0 | K20: =H20+I20-J20 -> 1124534.5
B21: Rate of GST for the Car | D21: 0.18 | F21: 48 | G21: ='4 Year RV @ 5% FL'!I48 -> 24362.948 | H21: =G21*F21 -> 1169421.5 | I21: 0 | J21: 0 | K21: =H21+I21-J21 -> 1169421.5
B22: Personal Income Tax | D22: 0.312 | F22: 60 | G22: ='5 Year RV @ 1% FL'!I18 -> 20256.985 | H22: =G22*F22 -> 1215419.1 | I22: 0 | J22: 0 | K22: =H22+I22-J22 -> 1215419.1
B23: Interest Rate for Loan | D23: 0.0825

Sheet 3 Year RV @ 10% FL
B2: Lease Workings | G2: Loan Workings
P3: 0.29
B4: Lease Rental (per month per lac) | D4: =+IF(D7>0.18,3355,3305) -> 3305 | G4: Funding Amount | I4: =Summary!D18 -> 1000000 | P4: 0.31
B5: Tenure (in months) | D5: 36 | G5: Tenure (in months) | I5: =+D5 -> 36 | P5: 0.43
B6: Personal Income Tax Rate | D6: =Summary!D22 -> 0.312 | G6: Personal Income Tax Rate | I6: =+D6 -> 0.312 | P6: 0.45
B7: Rate of GST | D7: =Summary!D21 -> 0.18 | G7: Interest Rate | I7: =Summary!D23 -> 0.0825 | P7: 0.48
B8: End Sale Value (% of cost) | D8: 0.1 | G8: EMI | I8: =PMT(I7/12,I5,-I4,0,1) -> 31237.069 | P8: 0.5
B9: Capitalization Amount | D9: =Summary!D19 -> 847457.63
B11: Gross Lease Outflow | D11: =+E56 -> 1289800 | F11: =I13-D13 -> 205952.07
B12: (-) Income Tax Saving | D12: =+E54*D6 -> 371217.6
B13: Effective Lease Outflow | D13: =+D11-D12 -> 918582.4 | G13: Effective Loan Outflow | I13: =+I54 -> 1124534.5
B16: Month | C16: Lease Rental | D16: =+"GST on Rentals @ "&+D7*100&"%" -> GST on Rentals @ 18% | E16: Total Cash Outflow | G16: Month | I16: Total Cash Outflow
B18: 1 | C18: =+$D$4*$D$9/100000 -> 28008.475 | D18: =+C18*$D$7 -> 5041.5254 | E18: =+C18+D18 -> 33050 | G18: 1 | I18: =+I8 -> 31237.069
B19: =+B18+1 -> 2 | C19: =+C18 -> 28008.475 | D19: =+C19*$D$7 -> 5041.5254 | E19: =+C19+D19 -> 33050 | G19: =+G18+1 -> 2 | I19: =+I18 -> 31237.069
B20: =+B19+1 -> 3 | C20: =+C19 -> 28008.475 | D20: =+C20*$D$7 -> 5041.5254 | E20: =+C20+D20 -> 33050 | G20: =+G19+1 -> 3 | I20: =+I19 -> 31237.069
B21: =+B20+1 -> 4 | C21: =+C20 -> 28008.475 | D21: =+C21*$D$7 -> 5041.5254 | E21: =+C21+D21 -> 33050 | G21: =+G20+1 -> 4 | I21: =+I20 -> 31237.069
B22: =+B21+1 -> 5 | C22: =+C21 -> 28008.475 | D22: =+C22*$D$7 -> 5041.5254 | E22: =+C22+D22 -> 33050 | G22: =+G21+1 -> 5 | I22: =+I21 -> 31237.069
B23: =+B22+1 -> 6 | C23: =+C22 -> 28008.475 | D23: =+C23*$D$7 -> 5041.5254 | E23: =+C23+D23 -> 33050 | G23: =+G22+1 -> 6 | I23: =+I22 -> 31237.069
B24: =+B23+1 -> 7 | C24: =+C23 -> 28008.475 | D24: =+C24*$D$7 -> 5041.5254 | E24: =+C24+D24 -> 33050 | G24: =+G23+1 -> 7 | I24: =+I23 -> 31237.069
B25: =+B24+1 -> 8 | C25: =+C24 -> 28008.475 | D25: =+C25*$D$7 -> 5041.5254 | E25: =+C25+D25 -> 33050 | G25: =+G24+1 -> 8 | I25: =+I24 -> 31237.069
B26: =+B25+1 -> 9 | C26: =+C25 -> 28008.475 | D26: =+C26*$D$7 -> 5041.5254 | E26: =+C26+D26 -> 33050 | G26: =+G25+1 -> 9 | I26: =+I25 -> 31237.069
B27: =+B26+1 -> 10 | C27: =+C26 -> 28008.475 | D27: =+C27*$D$7 -> 5041.5254 | E27: =+C27+D27 -> 33050 | G27: =+G26+1 -> 10 | I27: =+I26 -> 31237.069
B28: =+B27+1 -> 11 | C28: =+C27 -> 28008.475 | D28: =+C28*$D$7 -> 5041.5254 | E28: =+C28+D28 -> 33050 | G28: =+G27+1 -> 11 | I28: =+I27 -> 31237.069
B29: =+B28+1 -> 12 | C29: =+C28 -> 28008.475 | D29: =+C29*$D$7 -> 5041.5254 | E29: =+C29+D29 -> 33050 | G29: =+G28+1 -> 12 | I29: =+I28 -> 31237.069
B30: =+B29+1 -> 13 | C30: =+C29 -> 28008.475 | D30: =+C30*$D$7 -> 5041.5254 | E30: =+C30+D30 -> 33050 | G30: =+G29+1 -> 13 | I30: =+I29 -> 31237.069
... B53: =+B52+1 -> 36 | C53: =+C52 -> 28008.475 | D53: =+C53*$D$7 -> 5041.5254 | E53: =+C53+D53 -> 33050 | G53: =+G52+1 -> 36 | I53: =+I52 -> 31237.069
C54: =SUM(C18:C53) -> 1008305.1 | D54: =SUM(D18:D53) -> 181494.92 | E54: =SUM(E18:E53) -> 1189800 | G54: Gross Outflow | I54: =+SUM(I18:I53) -> 1124534.5
B55: End Sale Value | C55: =+D9*D8 -> 84745.763 | D55: =C55*$D$7 -> 15254.237 | E55: =+C55+D55 -> 100000
B56: Gross Outflow | E56: =+E54+E55 -> 1289800

Sheet 4 Year RV @ 5% FL
B2: Lease Workings | G2: Loan Workings | P2: 0.29
P3: 0.31
B4: Lease Rental (per month per lac) | D4: =+IF(D7>0.18,2770,2720) -> 2720 | G4: Funding Amount | I4: =Summary!D18 -> 1000000 | P4: 0.43
B5: Tenure (in months) | D5: 48 | G5: Tenure (in months) | I5: =+D5 -> 48 | P5: 0.45
B6: Personal Income Tax Rate | D6: =Summary!D22 -> 0.312 | G6: Personal Income Tax Rate | I6: 0.312 | P6: 0.48
B7: Rate of GST | D7: =Summary!D21 -> 0.18 | G7: Interest Rate | I7: =Summary!D23 -> 0.0825 | P7: 0.5
B8: End Sale Value (% of cost) | D8: 0.05 | G8: EMI | I8: =PMT(I7/12,I5,-I4,0,1) -> 24362.948
B9: Capitalization Amount | D9: =Summary!D19 -> 847457.63
B11: Gross Lease Outflow | D11: =+E68 -> 1355600
B12: (-) Income Tax Saving | D12: =+E66*D6 -> 407347.2
B13: Effective Lease Outflow | D13: =+D11-D12 -> 948252.8 | E13: =I13-D13 -> 221168.69 | G13: Effective Loan Outflow | I13: =+I66 -> 1169421.5
B16: Month | C16: Lease Rental | D16: =+"GST on Rentals @ "&+D7*100&"%" -> GST on Rentals @ 18% | E16: Total Cash Outflow | G16: Month | I16: Total Cash Outflow
B18: 1 | C18: =+$D$4*$D$9/100000 -> 23050.847 | D18: =+C18*$D$7 -> 4149.1525 | E18: =+C18+D18 -> 27200 | G18: 1 | I18: =+I8 -> 24362.948
B19: =+B18+1 -> 2 | C19: =+C18 -> 23050.847 | D19: =+C19*$D$7 -> 4149.1525 | E19: =+C19+D19 -> 27200 | G19: =+G18+1 -> 2 | I19: =+I18 -> 24362.948
B20: =+B19+1 -> 3 | C20: =+C19 -> 23050.847 | D20: =+C20*$D$7 -> 4149.1525 | E20: =+C20+D20 -> 27200 | G20: =+G19+1 -> 3 | I20: =+I19 -> 24362.948
B21: =+B20+1 -> 4 | C21: =+C20 -> 23050.847 | D21: =+C21*$D$7 -> 4149.1525 | E21: =+C21+D21 -> 27200 | G21: =+G20+1 -> 4 | I21: =+I20 -> 24362.948
B22: =+B21+1 -> 5 | C22: =+C21 -> 23050.847 | D22: =+C22*$D$7 -> 4149.1525 | E22: =+C22+D22 -> 27200 | G22: =+G21+1 -> 5 | I22: =+I21 -> 24362.948
B23: =+B22+1 -> 6 | C23: =+C22 -> 23050.847 | D23: =+C23*$D$7 -> 4149.1525 | E23: =+C23+D23 -> 27200 | G23: =+G22+1 -> 6 | I23: =+I22 -> 24362.948
B24: =+B23+1 -> 7 | C24: =+C23 -> 23050.847 | D24: =+C24*$D$7 -> 4149.1525 | E24: =+C24+D24 -> 27200 | G24: =+G23+1 -> 7 | I24: =+I23 -> 24362.948
B25: =+B24+1 -> 8 | C25: =+C24 -> 23050.847 | D25: =+C25*$D$7 -> 4149.1525 | E25: =+C25+D25 -> 27200 | G25: =+G24+1 -> 8 | I25: =+I24 -> 24362.948
B26: =+B25+1 -> 9 | C26: =+C25 -> 23050.847 | D26: =+C26*$D$7 -> 4149.1525 | E26: =+C26+D26 -> 27200 | G26: =+G25+1 -> 9 | I26: =+I25 -> 24362.948
B27: =+B26+1 -> 10 | C27: =+C26 -> 23050.847 | D27: =+C27*$D$7 -> 4149.1525 | E27: =+C27+D27 -> 27200 | G27: =+G26+1 -> 10 | I27: =+I26 -> 24362.948
B28: =+B27+1 -> 11 | C28: =+C27 -> 23050.847 | D28: =+C28*$D$7 -> 4149.1525 | E28: =+C28+D28 -> 27200 | G28: =+G27+1 -> 11 | I28: =+I27 -> 24362.948
B29: =+B28+1 -> 12 | C29: =+C28 -> 23050.847 | D29: =+C29*$D$7 -> 4149.1525 | E29: =+C29+D29 -> 27200 | G29: =+G28+1 -> 12 | I29: =+I28 -> 24362.948
B30: =+B29+1 -> 13 | C30: =+C29 -> 23050.847 | D30: =+C30*$D$7 -> 4149.1525 | E30: =+C30+D30 -> 27200 | G30: =+G29+1 -> 13 | I30: =+I29 -> 24362.948
... B65: =+B64+1 -> 48 | C65: =+C64 -> 23050.847 | D65: =+C65*$D$7 -> 4149.1525 | E65: =+C65+D65 -> 27200 | G65: =+G64+1 -> 48 | I65: =+I64 -> 24362.948
C66: =SUM(C18:C65) -> 1106440.7 | D66: =SUM(D18:D65) -> 199159.32 | E66: =SUM(E18:E65) -> 1305600 | G66: Gross Outflow | I66: =+SUM(I18:I65) -> 1169421.5
B67: End Sale Value | C67: =+D9*D8 -> 42372.881 | D67: =C67*$D$7 -> 7627.1186 | E67: =+C67+D67 -> 50000
B68: Gross Outflow | E68: =+E66+E67 -> 1355600

Sheet 5 Year  RV @ 1% FL
B2: Lease Workings | G2: Loan Workings | P2: 0.29
P3: 0.31
B4: Lease Rental (per month per lac) | D4: =+IF(D7>0.18,2405,2355) -> 2355 | G4: Funding Amount | I4: =Summary!D18 -> 1000000 | P4: 0.43
B5: Tenure (in months) | D5: 60 | G5: Tenure (in months) | I5: =+D5 -> 60 | P5: 0.45
B6: Personal Income Tax Rate | D6: =Summary!D22 -> 0.312 | G6: Personal Income Tax Rate | I6: =+D6 -> 0.312 | P6: 0.48
B7: Rate of GST | D7: =Summary!D21 -> 0.18 | G7: Interest Rate | I7: =Summary!D23 -> 0.0825 | P7: 0.5
B8: End Sale Value (% of cost) | D8: 0.01 | G8: EMI | I8: =PMT(I7/12,I5,-I4,0,1) -> 20256.985
B9: Capitalization Amount | D9: =Summary!D19 -> 847457.63
B11: Gross Lease Outflow | D11: =+E80 -> 1423000
B12: (-) Income Tax Saving | D12: =+E78*D6 -> 440856 | F12: =I13-D13 -> 233275.09
B13: Effective Lease Outflow | D13: =+D11-D12 -> 982144 | G13: Effective Loan Outflow | I13: =+I78 -> 1215419.1
B16: Month | C16: Lease Rental | D16: =+"GST on Rentals @ "&+D7*100&"%" -> GST on Rentals @ 18% | E16: Total Cash Outflow | G16: Month | I16: Total Cash Outflow
B18: 1 | C18: =+$D$4*$D$9/100000 -> 19957.627 | D18: =+C18*$D$7 -> 3592.3729 | E18: =+C18+D18 -> 23550 | G18: 1 | I18: =+I8 -> 20256.985
B19: =+B18+1 -> 2 | C19: =+C18 -> 19957.627 | D19: =+C19*$D$7 -> 3592.3729 | E19: =+C19+D19 -> 23550 | G19: =+G18+1 -> 2 | I19: =+I18 -> 20256.985
B20: =+B19+1 -> 3 | C20: =+C19 -> 19957.627 | D20: =+C20*$D$7 -> 3592.3729 | E20: =+C20+D20 -> 23550 | G20: =+G19+1 -> 3 | I20: =+I19 -> 20256.985
B21: =+B20+1 -> 4 | C21: =+C20 -> 19957.627 | D21: =+C21*$D$7 -> 3592.3729 | E21: =+C21+D21 -> 23550 | G21: =+G20+1 -> 4 | I21: =+I20 -> 20256.985
B22: =+B21+1 -> 5 | C22: =+C21 -> 19957.627 | D22: =+C22*$D$7 -> 3592.3729 | E22: =+C22+D22 -> 23550 | G22: =+G21+1 -> 5 | I22: =+I21 -> 20256.985
B23: =+B22+1 -> 6 | C23: =+C22 -> 19957.627 | D23: =+C23*$D$7 -> 3592.3729 | E23: =+C23+D23 -> 23550 | G23: =+G22+1 -> 6 | I23: =+I22 -> 20256.985
B24: =+B23+1 -> 7 | C24: =+C23 -> 19957.627 | D24: =+C24*$D$7 -> 3592.3729 | E24: =+C24+D24 -> 23550 | G24: =+G23+1 -> 7 | I24: =+I23 -> 20256.985
B25: =+B24+1 -> 8 | C25: =+C24 -> 19957.627 | D25: =+C25*$D$7 -> 3592.3729 | E25: =+C25+D25 -> 23550 | G25: =+G24+1 -> 8 | I25: =+I24 -> 20256.985
B26: =+B25+1 -> 9 | C26: =+C25 -> 19957.627 | D26: =+C26*$D$7 -> 3592.3729 | E26: =+C26+D26 -> 23550 | G26: =+G25+1 -> 9 | I26: =+I25 -> 20256.985
B27: =+B26+1 -> 10 | C27: =+C26 -> 19957.627 | D27: =+C27*$D$7 -> 3592.3729 | E27: =+C27+D27 -> 23550 | G27: =+G26+1 -> 10 | I27: =+I26 -> 20256.985
B28: =+B27+1 -> 11 | C28: =+C27 -> 19957.627 | D28: =+C28*$D$7 -> 3592.3729 | E28: =+C28+D28 -> 23550 | G28: =+G27+1 -> 11 | I28: =+I27 -> 20256.985
B29: =+B28+1 -> 12 | C29: =+C28 -> 19957.627 | D29: =+C29*$D$7 -> 3592.3729 | E29: =+C29+D29 -> 23550 | G29: =+G28+1 -> 12 | I29: =+I28 -> 20256.985
B30: =+B29+1 -> 13 | C30: =+C29 -> 19957.627 | D30: =+C30*$D$7 -> 3592.3729 | E30: =+C30+D30 -> 23550 | G30: =+G29+1 -> 13 | I30: =+I29 -> 20256.985
... B77: =+B76+1 -> 60 | C77: =+C76 -> 19957.627 | D77: =+C77*$D$7 -> 3592.3729 | E77: =+C77+D77 -> 23550 | G77: =+G76+1 -> 60 | I77: =+I76 -> 20256.985
C78: =SUM(C18:C77) -> 1197457.6 | D78: =SUM(D18:D77) -> 215542.37 | E78: =SUM(E18:E77) -> 1413000 | G78: Gross Outflow | I78: =+SUM(I18:I77) -> 1215419.1
B79: End Sale Value | C79: =+D9*D8 -> 8474.5763 | D79: =C79*$D$7 -> 1525.4237 | E79: =+C79+D79 -> 10000
B80: Gross Outflow | E80: =+E78+E79 -> 1423000

Sheet Comparision Lease Vs Loan Tax I
G1: =E1*12 -> 0
C2: With out car policy | G2: With Car policy
B3: S.No | C3: Component | D3: Contribution | F3: S.No | G3: Component | H3: Contribution
B4: 1 | C4: Fixed CTC | D4: 0 | F4: 1 | G4: Fixed CTC | H4: =D4 -> 0 | Q4: Small (29%-31%) | R4: Big (43% - 50%)
B5: 2 | C5: Basic per Annum | D5: =D4*30/100 -> 0 | F5: 2 | G5: Basic | H5: =D5 -> 0 | N5: Lease rental | O5: =K9 -> 23550 | P5: 3 | Q5: =(($O$5/(1.29))*100000/Q$12)*(1.29) -> 663380.28 | R5: =(($O$5/(1.45))*100000/Q$13)*(1.45) -> 654166.67 | Y5: Note: You can consider the total Deduction of Car Lease amount cannot exceed 25% (including car component, Driver charges, Fuel & maintenance reimbursements) of the employees annual Fixed CTC
B6: 3 | C6: HRA per Annum | D6: =D4*15/100 -> 0 | F6: 3 | G6: HRA | H6: =D6 -> 0 | J6: Tenure | K6: 5 | P6: 4 | Q6: =(($O$5/(1.29))*100000/R$12)*(1.29) -> 861060.33 | R6: =(($O$5/(1.45))*100000/R$13)*(1.45) -> 845601.44
B7: 4 | C7: Other salary Components PA | D7: =D4*33/100 -> 0 | F7: 4 | G7: Car Component | H7: =K9*12 -> 282600 | J7: GST | K7: =Summary!D21 -> 0.18 | P7: 5 | Q7: =(($O$5/(1.29))*100000/S$12)*(1.29) -> 1046666.7 | R7: =(($O$5/(1.45))*100000/S$13)*(1.45) -> 1023913
B8: 5 | C8: EPF | D8: =D5*12% -> 0 | F8: 5 | G8: Driver Allowance | H8: 180000
F9: =F8+1 -> 6 | G9: Balance Flexi | H9: =D7-H7-H8 -> -462600 | J9: Lease Rental Per Month | K9: =CHOOSE(K6-2,Summary!G14,Summary!G15,Summary!G16) -> 23550
B10: 6 | C10: Standard Deduction (new) | D10: 75000 | F10: =F9+1 -> 7 | G10: Annual Taxable Perquisite | H10: =(1800*12) -> 21600 | J10: Car Value (Ex-Showroom) | K10: =Summary!D18 -> 1000000
B11: 7 | C11: Taxable Salary (new) | D11: =D4-D10-D8 -> -75000 | F11: =F10+1 -> 8 | G11: EPF | H11: =D8 -> 0 | J11: Loan Value | K11: =K10 -> 1000000 | Q11: 3 Years | R11: 4 Years | S11: 5 Years
B12: 8 | C12: Tax payable new Regime | D12: ='New Tax Workings Overview'!D21 -> 0 | F12: =F11+1 -> 9 | G12: Standard Deduction (new) | H12: 75000 | K12: ` | P12: Small | Q12: 3550 | R12: 2735 | S12: 2250
B13: 9 | C13: Take home/ month new regime | D13: =((D5+D6+D7)-(D8+D12))/12 -> 0 | F13: =F12+1 -> 10 | G13: Taxable Salary (new) | H13: =H4-H7-H8-H11-H12+H10 -> -516000 | P13: Big | Q13: =Q12+50 -> 3600 | R13: =R12+50 -> 2785 | S13: =S12+50 -> 2300
B14: 10 | C14: Tax per month (new) | D14: =D12/12 -> 0 | F14: =F13+1 -> 11 | G14: Tax payable new Regime | H14: ='New Tax Workings Overview'!I21 -> 0
B15: 11 | C15: Car Loan EMI | D15: =PMT(Summary!D23/12,K6*12,-K11,0,1) -> 20256.985 | F15: =F14+1 -> 12 | G15: Tax per month (new) | H15: =H14/12 -> 0 | P15: Car Value (Ex-Showroom) | Q15: =K10 -> 1000000 | R15: =IF(Q16<21000,'[1]Allowance & Eligible Car Value'!C2,0) -> 0
B16: 12 | C16: Take home/ month after car New | D16: =D13-D15 -> -20256.985 | F16: =F15+1 -> 13 | G16: Take home/ month new regime | H16: =((H5+H6+H9+H8)-(H11+H14))/12 -> -23550 | J16: Δ (Delta) | P16: Lease Rental Per Month | Q16: =K9 -> 23550
J17: Tax Payable (New) | K17: =D12-H14 -> 0 | P17: Loan Value @ 99% | Q17: =Q15*0.99 -> 990000
G18: Increase in take home per month | H18: =H16-D16 -> -3293.0151
G19: Increase in take home per year | H19: =H18*12 -> -39516.181 | J19: Tax per Mon (New) | K19: =K17/12 -> 0
G20: Increase in take home per tenure | H20: =H19*K6 -> -197580.91
C23: Note: Car Perquisite value for upto 1600 CC cars Rs 1800/- per month & more than 1600 CC cars Rs 2400/- per month
C24: Driver perquisite value if availed will be 900/- per month

Sheet New Tax Workings Overview
A1: Income tax Calculator
A3: Taxable Salary (new) before Car Lease policy | C3: ='Comparision Lease Vs Loan Tax I'!D11 -> -75000 | F3: Taxable Salary (new) with car lease policy | H3: ='Comparision Lease Vs Loan Tax I'!H13 -> -516000
A5: New regime | F5: New regime
A6: < Rs. 4 L | B6: 400000 | C6: 0 | D6: =B6*C6 -> 0 | F6: < Rs. 4 L | G6: 400000 | H6: 0 | I6: =G6*H6 -> 0
A7: Rs. 4.01 L- Rs.8 L | B7: 800000 | C7: =5%*1 -> 0.05 | D7: =IF($C$3<1200000,0,IF($C$3>B7,(B7-B6)*C7,($C$3-B6)*C7)) -> 0 | F7: Rs. 4.01 L- Rs.8 L | G7: 800000 | H7: =5%*1 -> 0.05 | I7: =IF($H$3<1200000,0,IF($H$3>G7,(G7-G6)*H7,($H$3-G6)*H7)) -> 0
A8: Rs. 8.01 L- Rs.12 L | B8: 1200000 | C8: =10%*1 -> 0.1 | D8: =IF(C3<1200000,0,(IF($C$3>B8,(B8-B7)*C8,(IF(($C$3-B7)*C8>0,($C$3-B7)*C8,0))))) -> 0 | F8: Rs. 8.01 L- Rs.12 L | G8: 1200000 | H8: =10%*1 -> 0.1 | I8: =IF(H3<1200000,0,(IF($H$3>G8,(G8-G7)*H8,(IF(($H$3-G7)*H8>0,($H$3-G7)*H8,0))))) -> 0
A9: Rs. 12.01 L- Rs.16 L | B9: 1600000 | C9: =15%*1 -> 0.15 | D9: =IF(C3<1200000,0,(IF($C$3>B9,(B9-B8)*C9,(IF(($C$3-B8)*C9>0,($C$3-B8)*C9,0))))) -> 0 | F9: Rs. 12.01 L- Rs.16 L | G9: 1600000 | H9: =15%*1 -> 0.15 | I9: =IF(H3<1200000,0,(IF($H$3>G9,(G9-G8)*H9,(IF(($H$3-G8)*H9>0,($H$3-G8)*H9,0))))) -> 0
A10: Rs. 16.01 L- Rs.20 L | B10: 2000000 | C10: =20%*1 -> 0.2 | D10: =IF(C3<1200000,0,(IF($C$3>B10,(B10-B9)*C10,(IF(($C$3-B9)*C10>0,($C$3-B9)*C10,0))))) -> 0 | F10: Rs. 16.01 L- Rs.20 L | G10: 2000000 | H10: =20%*1 -> 0.2 | I10: =IF(H3<1200000,0,(IF($H$3>G10,(G10-G9)*H10,(IF(($H$3-G9)*H10>0,($H$3-G9)*H10,0))))) -> 0
A11: Rs. 20.01 L- Rs.24 L | B11: 2400000 | C11: =25%*1 -> 0.25 | D11: =IF(C3<1200000,0,(IF($C$3>B11,(B11-B10)*C11,(IF(($C$3-B10)*C11>0,($C$3-B10)*C11,0))))) -> 0 | F11: Rs. 20.01 L- Rs.24 L | G11: 2400000 | H11: =25%*1 -> 0.25 | I11: =IF(H3<1200000,0,(IF($H$3>G11,(G11-G10)*H11,(IF(($H$3-G10)*H11>0,($H$3-G10)*H11,0))))) -> 0
A12: > Rs. 24 L | B12: 2400000 | C12: =30%*1 -> 0.3 | D12: =IF(C3<1200000,0,(IF($C$3>B13,(B13-B12)*C12,(IF(($C$3-B12)*C12>0,($C$3-B12)*C12,0))))) -> 0 | F12: > Rs. 24 L | G12: 2400000 | H12: =30%*1 -> 0.3 | I12: =IF(H3<1200000,0,(IF($H$3>G13,(G13-G12)*H12,(IF(($H$3-G12)*H12>0,($H$3-G12)*H12,0))))) -> 0
A13: > Rs. 50 L | B13: 5000000 | C13: =30%*1*1 -> 0.3 | D13: =IF(C3<1200000,0,(IF($C$3>B14,(B14-B13)*C13,(IF(($C$3-B13)*C13>0,($C$3-B13)*C13,0))))) -> 0 | F13: > Rs. 50 L | G13: 5000000 | H13: =30%*1*1 -> 0.3 | I13: =IF(H3<1200000,0,(IF($H$3>G14,(G14-G13)*H13,(IF(($H$3-G13)*H13>0,($H$3-G13)*H13,0))))) -> 0
A14: > Rs. 100 L | B14: 10000000 | C14: =30%*1*1 -> 0.3 | D14: =IF(C3<1200000,0,(IF($C$3>B15,(B15-B14)*C14,(IF(($C$3-B14)*C14>0,($C$3-B14)*C14,0))))) -> 0 | F14: > Rs. 100 L | G14: 10000000 | H14: =30%*1*1 -> 0.3 | I14: =IF(H3<1200000,0,(IF($H$3>G15,(G15-G14)*H14,(IF(($H$3-G14)*H14>0,($H$3-G14)*H14,0))))) -> 0
A15: > Rs. 200 L | B15: 20000000 | C15: =30%*1*1 -> 0.3 | D15: =IF(C3<1200000,0,IF(C3>B15,(C3-B15)*C15,0)) -> 0 | F15: > Rs. 200 L | G15: 20000000 | H15: =30%*1*1 -> 0.3 | I15: =IF(H3<1200000,0,IF(H3>G15,(H3-G15)*H15,0)) -> 0
B17: Tax payable | D17: =IF(C3>1200000,SUM(D6:D16),0) -> 0 | G17: Tax payable | I17: =IF(H3>1200000,SUM(I6:I16),0) -> 0
B18: Cess | D18: =D17*4% -> 0 | G18: Cess | I18: =I17*4% -> 0
B19: Surcharge | D19: =IF(C3<B13,0,IF(C3<B14,D17*10%,IF(C3<B15,D17*15%,D17*25%))) -> 0 | G19: Surcharge | I19: =IF(H3<G13,0,IF(H3<G14,I17*10%,IF(H3<G15,I17*15%,I17*25%))) -> 0
B20: Cess | D20: =D19*4% -> 0 | G20: Cess | I20: =I19*4% -> 0
B21: Total Tax | D21: =SUM(D17:D20) -> 0 | G21: Total Tax | I21: =SUM(I17:I20) -> 0

Sheet Allowance & Eligible Car Value
A1: Monthly Allowance | B1: Year | C1: Approx - Ex-Showroom Value
A2: 20000 | B2: 3 Years | C2: 570000
A3: 20000 | B3: 4 Years | C3: 735000
A4: 20000 | B4: 5 Years | C4: 890000
A5: 30000 | B5: 3 Years | C5: 850000
A6: 30000 | B6: 4 Years | C6: 1100000
A7: 30000 | B7: 5 Years | C7: 1330000
A8: 35000 | B8: 3 Years | C8: 986000
A9: 35000 | B9: 4 Years | C9: 1280000
A10: 35000 | B10: 5 Years | C10: 1560000
A11: 45000 | B11: 3 Years | C11: 1270000
A12: 35000 | B12: 4 Years | C12: 1650000
A13: 35000 | B13: 5 Years | C13: 2000000
... A28: 35000 | B28: 5 Years | C28: 4225000
